poco/__init__.py
poco/acceleration.py
poco/agent.py
poco/agent.pyi
poco/exceptions.py
poco/gesture.py
poco/global_state.py
poco/pocofw.py
poco/pocofw.pyi
poco/proxy.py
poco/proxy.pyi
poco/drivers/__init__.py
poco/drivers/android/__init__.py
poco/drivers/android/uiautomation.py
poco/drivers/android/lib/pocoservice-debug.apk
poco/drivers/android/utils/__init__.py
poco/drivers/android/utils/installation.py
poco/drivers/cocosjs/__init__.py
poco/drivers/cocosjs/test/__init__.py
poco/drivers/cocosjs/test/simple.py
poco/drivers/ios/__init__.py
poco/drivers/netease/__init__.py
poco/drivers/netease/internal.py
poco/drivers/osx/__init__.py
poco/drivers/osx/osxui_poco.py
poco/drivers/osx/sdk/OSXUI.py
poco/drivers/osx/sdk/OSXUIDumper.py
poco/drivers/osx/sdk/OSXUIFunc.py
poco/drivers/osx/sdk/OSXUINode.py
poco/drivers/osx/sdk/__init__.py
poco/drivers/qt/__init__.py
poco/drivers/std/HierarchyTranslator.py
poco/drivers/std/__init__.py
poco/drivers/std/attributor.py
poco/drivers/std/dumper.py
poco/drivers/std/inputs.py
poco/drivers/std/screen.py
poco/drivers/std/test/__init__.py
poco/drivers/std/test/simple.py
poco/drivers/ue4/__init__.py
poco/drivers/ue4/device.py
poco/drivers/ue4/ue4_poco.py
poco/drivers/unity3d/__init__.py
poco/drivers/unity3d/device.py
poco/drivers/unity3d/unity3d_poco.py
poco/drivers/unity3d/test/__init__.py
poco/drivers/unity3d/test/test.py
poco/drivers/unity3d/test/tutorial/__init__.py
poco/drivers/unity3d/test/tutorial/buttons_and_labels.py
poco/drivers/unity3d/test/tutorial/case.py
poco/drivers/unity3d/test/tutorial/click.py
poco/drivers/unity3d/test/tutorial/drag.py
poco/drivers/unity3d/test/tutorial/exception1.py
poco/drivers/unity3d/test/tutorial/exception2.py
poco/drivers/unity3d/test/tutorial/exception3.py
poco/drivers/unity3d/test/tutorial/frozen_ui.py
poco/drivers/unity3d/test/tutorial/local_positioning1.py
poco/drivers/unity3d/test/tutorial/local_positioning2.py
poco/drivers/unity3d/test/tutorial/local_positioning3.py
uwa_pocoui-1.6.1085.dist-info/LICENSE
uwa_pocoui-1.6.1085.dist-info/METADATA
uwa_pocoui-1.6.1085.dist-info/WHEEL
uwa_pocoui-1.6.1085.dist-info/top_level.txt
uwa_pocoui-1.6.1085.dist-info/RECORD
