Metadata-Version: 2.1
Name: uwa-pocoui
Version: 1.6.1085
Summary: Poco cross-engine UI automated test framework.
Home-page: https://github.com/AirtestProject/Poco
Author: Netease Games
Author-email: lxn3032@corp.netease.com, gzliuxin@corp.netease.com
License: Apache License 2.0
Keywords: poco,automation test,ui automation
License-File: LICENSE
Requires-Dist: six
Requires-Dist: requests
Requires-Dist: uwa-airtest
Requires-Dist: hrpc (>=1.0.9)
Requires-Dist: websocket-client (==0.48.0)
